optds_iv/__init__.py
optds_iv/backend.py
optds_iv/engine.py
optds_iv/py.typed
optds_iv-0.1.0.dist-info/METADATA
optds_iv-0.1.0.dist-info/WHEEL
optds_iv-0.1.0.dist-info/RECORD
