Metadata-Version: 2.4
Name: optds-iv
Version: 0.1.0
Summary: The Calculator. Implied volatility, Greeks, Surface interpolation. | `optds-core`, `scipy`, `numba`
Author-email: Raeid Saqur <raeid.saqur@maths.ox.ac.uk>
Requires-Python: >=3.10
Requires-Dist: numpy
Requires-Dist: optds-core==0.1.0
Requires-Dist: scipy
Provides-Extra: cuda
Requires-Dist: cupy-cuda12x; extra == 'cuda'
Provides-Extra: jax
Requires-Dist: jax[cuda12]; extra == 'jax'
